{"properties": [
  {
    "name": "external.law-domain-api.service-key",
    "type": "java.lang.String",
    "description": "A description for 'external.law-domain-api.service-key'"
  },
  {
    "name": "external.law-domain-api.path",
    "type": "java.lang.String",
    "description": "A description for 'external.law-domain-api.path'"
  },
  {
    "name": "external.law-instance-api.path",
    "type": "java.lang.String",
    "description": "A description for 'external.law-instance-api.path'"
  }
]}